text_to_sidc/__init__.py
text_to_sidc/austrian.py
text_to_sidc/patterns.py
text_to_sidc/patterns_data.csv
text_to_sidc-0.0.20.dist-info/METADATA
text_to_sidc-0.0.20.dist-info/WHEEL
text_to_sidc-0.0.20.dist-info/top_level.txt
text_to_sidc-0.0.20.dist-info/RECORD
