Metadata-Version: 2.1
Name: text_to_sidc
Version: 0.0.20
Summary: A library to convert name of object into sidc code
Home-page: https://github.com/NorwayPoppy/austrian_python
Author: Serhii Syrota
Author-email: ssyrota241@gmail.com
Requires-Python: >=3.10
Requires-Dist: setuptools ==70.2.0
Requires-Dist: regex ==2023.10.3
